<?xml version="1.0" ?>
<annotations>
  <meta>
    <task>
      <labels>
        <label>
          <name>person</name>
          <color>#c06060</color>
          <attributes/>
        </label>
        <label>
          <name>visible_corner</name>
          <color>#c1e0f5</color>
          <attributes/>
        </label>
        <label>
          <name>invisible_corner</name>
          <color>#aaf0d1</color>
          <attributes/>
        </label>
        <label>
          <name>content_red</name>
          <color>#fa3253</color>
          <attributes/>
        </label>
        <label>
          <name>content_black</name>
          <color>#000000</color>
          <attributes/>
        </label>
        <label>
          <name>content_blue</name>
          <color>#3d3df5</color>
          <attributes/>
        </label>
        <label>
          <name>content_green</name>
          <color>#24b353</color>
          <attributes/>
        </label>
        <label>
          <name>content_white</name>
          <color>#ffffff</color>
          <attributes/>
        </label>
        <label>
          <name>reflection</name>
          <color>#584eaf</color>
          <attributes/>
        </label>
        <label>
          <name>content</name>
          <color>#fa3253</color>
          <attributes/>
        </label>
        <label>
          <name>visible_mid_corner</name>
          <color>#7fbb7d</color>
          <attributes/>
        </label>
        <label>
          <name>invisible_mid_corner</name>
          <color>#89a408</color>
          <attributes/>
        </label>
        <label>
          <name>invisible_picture_edge</name>
          <color>#092488</color>
          <attributes/>
        </label>
        <label>
          <name>visible_picture_edge</name>
          <color>#5dcc6c</color>
          <attributes/>
        </label>
        <label>
          <name>board</name>
          <color>#ff6a4d</color>
          <attributes/>
        </label>
      </labels>
    </task>
    <frame_source type="image" path="DarkBoard/black_board_4.mp4_26-01.png">
      <image_file file="black_board_4.mp4_26-01.png"/>
    </frame_source>
  </meta>
  <image id="0" name="black_board_4.mp4_26-01" width="1280" height="720">
    <polygon label="content" occluded="0" source="manual" points="442.28,167.84;512.59,168.75;571.56,168.75;621.91,166.48;664.10,164.21;700.39,161.94;718.53,159.67;744.39,156.04;751.19,154.68;750.74,107.05;746.66,102.52;745.75,92.08;739.85,87.09;735.21,87.32;720.26,86.96;706.41,85.32;702.40,83.49;691.14,82.53;669.40,83.16;654.91,82.53;652.39,79.70;652.08,71.19;648.93,70.88;648.61,78.44;646.72,81.59;635.07,83.16;619.00,81.59;618.37,77.18;617.74,72.77;614.27,68.36;619.63,62.69;620.89,54.18;620.26,48.20;612.07,47.88;603.56,47.25;601.36,39.69;608.60,36.86;601.04,33.71;579.62,34.97;570.80,36.54;571.75,39.69;579.31,41.58;580.25,44.73;577.42,48.20;563.56,47.25;562.93,55.13;565.76,65.84;568.60,74.34;569.23,80.33;561.98,82.53;553.48,80.01;542.14,82.22;531.74,85.37;500.40,93.10;438.39,95.74;428.89,102.91;426.96,111.25;411.12,123.12;412.56,126.60;427.73,120.74;432.83,137.03;436.61,143.33;440.07,148.69;440.39,164.75" z_order="0">
      <attribute name="Difficult">true</attribute>
    </polygon>
    <polygon label="content" occluded="0" source="manual" points="932.64,75.30;929.46,88.91;934.00,98.89;939.44,99.80;949.88,98.44;950.33,127.47;953.16,221.83;954.73,305.70;960.22,467.96;960.31,545.25;959.44,570.64;956.69,572.60;954.79,578.80;956.56,581.96;963.53,581.84;992.07,582.99;1034.95,584.52;1067.11,585.40;1095.54,587.59;1133.17,588.68;1171.89,591.52;1207.11,593.71;1225.71,593.49;1235.33,593.71;1279.74,594.81;1279.20,111.59;1279.66,67.59;1129.06,70.31;1041.05,72.58;988.43,73.49;946.25,72.13;934.91,69.86" z_order="0">
      <attribute name="Difficult">true</attribute>
    </polygon>
    <polygon label="content" occluded="0" source="manual" points="495.80,345.46;496.01,356.66;551.16,354.59;550.96,343.39" z_order="0">
      <attribute name="Difficult">true</attribute>
    </polygon>
    <polygon label="content" occluded="0" source="manual" points="777.30,333.20;777.40,342.70;829.30,341.30;829.60,331.60" z_order="0">
      <attribute name="Difficult">true</attribute>
    </polygon>
    <polygon label="person" occluded="0" source="manual" points="488.33,385.48;486.26,391.08;486.67,397.30;486.67,405.18;483.36,403.94;482.73,407.26;482.73,412.85;482.73,419.07;485.84,421.56;492.89,425.30;493.72,431.72;494.55,435.46;489.16,438.57;485.84,441.68;483.15,446.03;481.90,448.73;485.22,454.74;482.73,456.40;478.38,459.72;475.06,461.17;472.16,461.17;467.18,462.62;463.03,464.28;459.30,465.73;455.98,468.43;451.22,470.50;447.48,473.61;443.54,477.55;441.88,481.90;441.05,486.05;439.40,491.65;437.74,496.83;434.21,502.23;432.97,507.20;432.55,510.73;431.72,513.42;430.48,517.78;428.61,522.75;426.12,526.07;426.54,529.80;425.09,533.74;423.22,538.10;420.53,544.11;419.07,545.77;418.66,549.92;418.25,553.86;419.28,555.52;424.26,556.35;426.33,558.63;430.06,558.84;432.35,559.46;434.83,561.12;437.53,562.36;441.26,563.40;432.20,559.80;432.20,559.90;436.60,570.70;436.20,574.20;435.30,576.20;434.30,579.20;433.10,582.40;432.55,586.41;431.72,588.90;430.27,592.01;428.82,598.23;428.20,603.83;427.99,608.39;426.75,615.03;425.71,619.18;424.26,621.87;422.60,624.36;422.60,626.85;422.60,629.96;423.43,634.11;421.98,638.46;419.28,643.02;417.83,646.96;417.21,649.66;416.17,653.60;412.85,654.01;412.23,656.29;411.19,662.10;412.85,667.08;408.71,670.39;404.97,673.09;401.86,674.54;398.13,676.82;393.78,679.52;390.67,681.80;387.76,685.32;387.56,689.47;387.56,694.03;388.39,698.80;391.08,701.91;393.15,705.65;394.61,708.76;398.75,711.24;405.60,711.87;411.61,711.24;412.65,709.17;413.06,705.02;409.33,703.16;407.46,701.71;409.33,697.56;413.68,693.62;416.38,689.47;420.53,686.78;422.81,683.04;422.81,678.69;424.88,673.71;429.24,668.32;431.10,661.48;431.72,657.54;432.97,653.81;436.70,652.56;437.53,650.42;438.91,647.48;440.99,643.85;442.71,638.84;444.61,634.52;447.55,629.34;451.35,625.19;453.43,621.73;454.46,616.90;457.57,614.48;460.17,614.82;463.62,617.41;465.18,621.91;465.00,627.78;465.70,632.10;465.07,634.77;465.81,639.50;465.32,645.97;464.32,653.93;463.57,662.89;463.08,670.35;458.60,672.59;457.60,680.80;457.85,688.77;458.35,694.49;455.96,697.82;455.06,702.30;455.66,707.08;454.47,711.86;453.27,717.83;453.27,720.22;593.96,719.12;596.90,707.68;593.02,694.54;591.82,683.49;589.73,672.14;589.98,661.89;588.99,650.20;587.74,640.49;586.00,630.29;585.00,623.82;579.28,617.10;576.54,608.64;578.29,602.42;582.27,597.69;583.26,584.26;580.77,577.04;573.31,573.31;573.81,561.12;575.30,549.17;575.80,539.47;578.29,535.74;583.51,537.23;584.51,542.20;584.51,546.19;588.49,549.92;592.72,550.42;598.69,549.92;605.16,545.19;611.38,534.49;617.73,524.00;621.25,511.97;626.43,504.09;627.47,491.44;631.54,483.73;635.02,475.27;640.24,470.54;644.97,466.56;647.71,455.86;647.96,447.65;645.47,440.68;640.24,438.19;632.78,436.95;627.55,436.70;625.56,439.69;624.07,445.41;619.84,448.15;616.85,452.13;615.11,459.34;616.36,467.06;615.36,474.52;614.37,481.24;612.13,489.95;607.65,498.16;601.43,507.62;596.70,503.64;593.22,495.42;591.47,488.95;590.23,481.49;586.99,478.50;582.52,476.76;577.04,479.00;574.06,474.77;571.32,472.53;567.09,472.53;565.60,475.77;562.11,471.54;561.61,465.56;555.89,464.07;550.67,466.06;551.16,460.09;547.18,452.87;542.45,455.11;541.71,450.14;541.21,444.91;540.46,437.94;540.21,431.23;543.45,428.49;545.94,429.73;551.16,424.01;550.42,418.04;550.91,412.07;554.15,407.84;557.13,401.86;556.39,394.65;555.14,386.44;552.66,379.72;550.42,375.24;546.68,370.26;541.71,367.77;533.99,365.04;526.53,362.80;520.56,363.54;515.83,363.79;509.86,364.29;500.15,365.04;493.43,371.26;489.70,376.98;488.46,382.21" z_order="0"/>
    <polyline label="content_white" occluded="0" source="manual" points="108.48,388.32;107.04,387.36;104.64,385.32;99.72,385.32;98.04,388.20;97.92,392.52;100.20,395.52;105.96,396.84;101.52,397.56;97.32,398.04;94.56,400.92;95.88,404.52;99.24,406.92;102.12,408.00;106.68,407.88" z_order="0"/>
    <polyline label="content_white" occluded="0" source="manual" points="112.68,396.60;115.68,399.96;117.96,402.48;121.92,406.20" z_order="0"/>
    <polyline label="content_white" occluded="0" source="manual" points="119.16,396.84;118.20,400.92;117.00,403.92;114.96,407.04;113.88,409.20" z_order="0"/>
    <polyline label="content_white" occluded="0" source="manual" points="129.20,398.00;128.80,400.10" z_order="0"/>
    <polyline label="content_white" occluded="0" source="manual" points="97.46,416.45;101.09,414.89;105.58,413.68;111.97,413.51;116.29,413.86;122.34,413.86;125.28,413.68" z_order="0"/>
    <polyline label="content_white" occluded="0" source="manual" points="159.12,396.72;161.42,393.84;164.16,393.84;165.60,396.72;163.01,400.03;160.85,403.34;160.99,406.37;164.74,406.66;167.90,406.22" z_order="0"/>
    <polyline label="content_white" occluded="0" source="manual" points="178.27,385.34;178.99,388.66;178.42,393.55;177.41,397.44;174.38,399.02;173.09,402.05;176.11,404.93;178.27,404.93;179.86,399.89;180.29,392.26;180.86,402.48;183.17,403.78" z_order="0"/>
    <polyline label="content_white" occluded="0" source="manual" points="222.77,404.78;218.30,406.22;211.54,408.67;206.35,409.97;203.04,410.83" z_order="0"/>
    <polyline label="content_white" occluded="0" source="manual" points="201.17,407.23;205.49,406.51;209.95,406.37;213.84,407.52;220.03,408.53" z_order="0"/>
    <polyline label="content_white" occluded="0" source="manual" points="235.01,384.34;231.41,384.05;227.09,385.20;223.63,387.65;221.62,391.54;222.48,395.42;225.65,399.46;228.96,402.05;234.00,403.78;238.32,403.20" z_order="0"/>
    <polyline label="content_white" occluded="0" source="manual" points="244.80,382.32;244.80,386.78;244.80,390.67;244.94,395.14;245.95,399.46;246.96,402.77" z_order="0"/>
    <polyline label="content_white" occluded="0" source="manual" points="245.23,382.90;248.26,383.18;252.58,383.33;257.04,383.62" z_order="0"/>
    <polyline label="content_white" occluded="0" source="manual" points="244.94,391.97;248.83,391.25;254.74,391.39;257.33,391.10" z_order="0"/>
    <polyline label="content_white" occluded="0" source="manual" points="280.66,380.59;280.94,384.19;280.66,389.95;280.66,395.28;281.66,400.03;281.09,402.77" z_order="0"/>
    <polyline label="content_white" occluded="0" source="manual" points="272.59,377.42;276.91,377.57;280.66,377.57;284.11,378.00" z_order="0"/>
    <polyline label="content_white" occluded="0" source="manual" points="149.71,434.42;149.92,438.57;150.54,445.62;151.79,451.42;152.62,457.23;153.24,463.45" z_order="0"/>
    <polyline label="content_white" occluded="0" source="manual" points="134.99,434.63;139.76,434.00;144.53,432.97;149.30,432.14;154.28,431.72;159.87,431.72" z_order="0"/>
    <polyline label="content_white" occluded="0" source="manual" points="165.27,445.41;169.21,445.41;174.80,445.62" z_order="0"/>
    <polyline label="content_white" occluded="0" source="manual" points="166.72,451.22;171.07,452.04;175.63,452.25" z_order="0"/>
    <polyline label="content_white" occluded="0" source="manual" points="203.30,429.48;198.82,429.98;193.09,433.47;190.11,436.95;186.87,440.68;184.88,445.41;186.38,451.38;189.11,456.11;193.84,459.59;199.81,460.59;205.54,457.60;210.26,452.63;212.75,445.66;213.25,439.19;213.50,433.22;209.27,429.98" z_order="0"/>
    <polyline label="content_white" occluded="0" source="manual" points="201.31,445.16;205.04,448.15;208.27,450.88;212.25,456.11;214.00,458.35" z_order="0"/>
    <polyline label="content_white" occluded="0" source="manual" points="230.30,424.30;227.20,428.20;225.20,432.70;224.20,437.10;223.10,441.30;222.90,446.10;222.80,451.30;223.10,454.90;223.90,458.40;226.00,461.00;228.50,463.10" z_order="0"/>
    <polyline label="content_white" occluded="0" source="manual" points="265.90,426.30;262.60,423.10;257.30,423.60;250.00,427.20;246.60,431.10;244.40,435.20;242.70,439.40;242.20,445.60;243.70,451.20;247.60,455.90;254.60,458.30;260.80,457.10;265.60,451.70;268.00,447.60;268.20,444.70" z_order="0"/>
    <polyline label="content_white" occluded="0" source="manual" points="257.50,443.50;264.10,443.40;269.50,443.10;276.00,442.80;280.10,442.20" z_order="0"/>
    <polyline label="content_white" occluded="0" source="manual" points="269.42,449.28;271.58,453.31;273.31,456.62" z_order="0"/>
    <polyline label="content_white" occluded="0" source="manual" points="239.47,445.82;249.98,446.11;256.61,446.26" z_order="0"/>
    <polyline label="content_white" occluded="0" source="manual" points="263.81,447.55;273.17,447.55;276.34,447.55" z_order="0"/>
    <polyline label="content_white" occluded="0" source="manual" points="293.62,416.88;298.22,418.90;301.97,422.06;302.83,426.38;303.26,432.43;302.83,437.62;301.68,441.07;299.23,444.10;296.93,446.83;295.06,448.56" z_order="0"/>
    <polyline label="content_white" occluded="0" source="manual" points="405.50,450.29;400.61,453.46;395.57,457.20;390.53,461.38;388.51,462.67;393.98,466.85;399.46,470.02;403.20,473.04" z_order="0"/>
    <polyline label="content_white" occluded="0" source="manual" points="175.08,490.92;168.48,492.24;162.00,493.44;153.12,495.12;144.00,497.64;134.64,501.84;129.36,505.20;123.24,508.08;116.28,513.84;111.72,520.68;107.76,525.96;105.84,531.84;105.12,537.00;104.76,541.92;105.00,549.00;106.56,554.52;108.60,559.92;112.32,564.48;117.36,568.68;123.12,572.28;132.60,575.28;140.88,575.16;151.92,574.68;160.20,571.44;169.08,568.92;175.80,566.76;183.96,564.96;190.56,563.52;200.04,562.08;208.80,562.32;219.60,563.28;228.24,564.00;243.36,566.04;254.16,567.84;265.56,569.76;273.00,570.48;282.60,570.60;291.00,571.20;303.24,569.04;313.56,566.04;319.56,563.52;326.64,559.20;334.08,552.84;339.96,546.36;343.80,540.84;346.20,535.56;348.24,528.84;348.84,522.00;349.32,514.44;347.28,507.72;344.52,501.96;341.64,497.04;338.04,492.84;331.44,488.16;324.36,485.52;316.80,483.84;309.72,482.88;297.96,483.36;289.44,484.32;277.44,486.60;270.48,487.92;260.76,490.56;250.08,492.36;241.44,493.20;229.44,493.68;221.04,493.20;210.96,492.00;204.36,490.32;198.72,489.84;192.24,489.12;185.88,490.08;179.88,491.76;177.60,491.52" z_order="0"/>
    <polyline label="content_white" occluded="0" source="manual" points="123.12,523.20;128.40,526.20;133.08,527.04;138.12,526.08;141.12,524.04;142.92,521.88;136.92,523.44" z_order="0"/>
    <polyline label="content_white" occluded="0" source="manual" points="166.20,530.28;163.44,534.24;163.80,537.12;168.36,538.44;173.52,537.60;177.36,536.28;179.40,533.16;179.28,530.40;176.76,528.72;172.08,528.48;167.88,529.08" z_order="0"/>
    <polyline label="content_white" occluded="0" source="manual" points="168.48,525.84;169.56,530.88;169.92,535.32;170.64,539.52" z_order="0"/>
    <polyline label="content_white" occluded="0" source="manual" points="169.10,545.00;170.50,543.10" z_order="0"/>
    <polyline label="content_white" occluded="0" source="manual" points="181.40,536.80;181.40,539.30" z_order="0"/>
    <polyline label="content_white" occluded="0" source="manual" points="212.80,540.60;211.10,542.00" z_order="0"/>
    <polyline label="content_white" occluded="0" source="manual" points="163.10,551.20;166.40,551.30;166.40,553.10;167.00,554.30;169.70,553.70;163.70,556.70;163.40,558.90;167.10,559.40" z_order="0"/>
    <polyline label="content_white" occluded="0" source="manual" points="176.10,555.40;176.70,557.80" z_order="0"/>
    <polyline label="content_white" occluded="0" source="manual" points="287.70,508.30;288.00,511.00;288.50,515.10;289.50,519.90" z_order="0"/>
    <polyline label="content_white" occluded="0" source="manual" points="286.70,512.50;282.80,513.10;281.50,516.10;283.50,519.00;287.90,520.30;292.00,519.60;295.00,518.50;296.30,515.90;294.80,513.40;291.30,511.80;288.10,512.50" z_order="0"/>
    <polyline label="content_white" occluded="0" source="manual" points="299.50,519.00;300.30,516.80;302.60,516.10;303.60,517.90;304.40,519.70" z_order="0"/>
    <polyline label="content_white" occluded="0" source="manual" points="286.40,533.20;289.70,532.30;292.10,532.70;292.70,534.70;291.30,537.30;289.70,540.10;289.90,543.20;292.60,544.60;295.60,544.10" z_order="0"/>
    <polyline label="content_white" occluded="0" source="manual" points="287.40,540.10;292.90,539.80;295.00,539.20" z_order="0"/>
    <polyline label="content_white" occluded="0" source="manual" points="301.00,542.90" z_order="0"/>
    <polyline label="content_white" occluded="0" source="manual" points="824.04,344.88;822.00,344.64;817.92,346.32;816.36,348.72;817.08,351.24;819.36,352.20;822.00,350.16;823.80,346.56;823.80,349.44;824.64,351.60" z_order="0"/>
    <polyline label="content_white" occluded="0" source="manual" points="847.68,338.76;850.56,340.08;848.40,341.76;849.84,343.44;852.36,345.00;854.16,346.80;853.80,348.36;852.00,349.20" z_order="0"/>
    <polygon label="board" occluded="0" source="manual" points="51.06,105.11;59.72,353.84;1223.96,302.08;1215.86,71.18" z_order="0"/>
    <points label="visible_corner" occluded="0" source="manual" points="51.12,105.00" z_order="0"/>
    <points label="visible_corner" occluded="0" source="manual" points="59.52,353.52" z_order="0"/>
    <polygon label="board" occluded="0" source="manual" points="67.39,368.06;75.17,642.99;1220.29,568.09;1214.70,314.24" z_order="0"/>
    <points label="visible_corner" occluded="0" source="manual" points="67.31,367.72" z_order="0"/>
    <points label="visible_corner" occluded="0" source="manual" points="75.02,642.33" z_order="0"/>
    <points label="invisible_corner" occluded="0" source="manual" points="1216.24,70.89" z_order="0"/>
    <points label="invisible_corner" occluded="0" source="manual" points="1224.05,301.41" z_order="0"/>
    <points label="invisible_corner" occluded="0" source="manual" points="1214.28,314.53" z_order="0"/>
    <points label="invisible_corner" occluded="0" source="manual" points="1220.42,567.93" z_order="0"/>
    <polygon label="content" occluded="0" source="manual" points="783.98,587.75;794.34,587.07;811.03,586.13;823.54,585.73;834.04,585.19;835.25,586.53;834.58,590.17;836.06,592.46;783.30,597.30;783.71,592.19" z_order="0">
      <attribute name="Difficult">true</attribute>
    </polygon>
    <points label="visible_mid_corner" occluded="0" source="manual" points="62.00,360.60" z_order="0"/>
    <points label="invisible_mid_corner" occluded="0" source="manual" points="1219.44,309.00" z_order="0"/>
  </image>
</annotations>
