<?xml version='1.0' encoding='utf-8'?>
<annotations>
  <version>1.1</version>
  <meta>
    <task>
      <id>3544</id>
      <name>blackboard_047.mp4_frame_600</name>
      <size>1</size>
      <mode>annotation</mode>
      <overlap>0</overlap>
      <bugtracker />
      <created>2022-03-06 19:42:41.805737+00:00</created>
      <updated>2022-03-22 12:32:47.259970+00:00</updated>
      <start_frame>0</start_frame>
      <stop_frame>0</stop_frame>
      <frame_filter />
      <labels>
        <label>
          <name>content</name>
          <color>#80f8bb</color>
          <attributes>
            <attribute>
              <name>Difficult</name>
              <mutable>False</mutable>
              <input_type>checkbox</input_type>
              <default_value>false</default_value>
              <values>false</values>
            </attribute>
          </attributes>
        </label>
        <label>
          <name>person</name>
          <color>#c06060</color>
          <attributes>
            <attribute>
              <name>hand_only</name>
              <mutable>False</mutable>
              <input_type>checkbox</input_type>
              <default_value>false</default_value>
              <values>false</values>
            </attribute>
          </attributes>
        </label>
        <label>
          <name>visible_corner</name>
          <color>#2a7dd1</color>
          <attributes>
          </attributes>
        </label>
        <label>
          <name>invisible_corner</name>
          <color>#3d3df5</color>
          <attributes>
          </attributes>
        </label>
        <label>
          <name>content_red</name>
          <color>#fa3253</color>
          <attributes>
          </attributes>
        </label>
        <label>
          <name>content_white</name>
          <color>#3df53d</color>
          <attributes>
          </attributes>
        </label>
        <label>
          <name>content_blue</name>
          <color>#3d3df5</color>
          <attributes>
          </attributes>
        </label>
        <label>
          <name>content_green</name>
          <color>#24b353</color>
          <attributes>
          </attributes>
        </label>
        <label>
          <name>reflection</name>
          <color>#f078f0</color>
          <attributes>
          </attributes>
        </label>
        <label>
          <name>invisible_mid_corner</name>
          <color>#89a408</color>
          <attributes>
          </attributes>
        </label>
        <label>
          <name>visible_mid_corner</name>
          <color>#64be70</color>
          <attributes>
          </attributes>
        </label>
        <label>
          <name>invisible_picture_edge</name>
          <color>#676770</color>
          <attributes>
          </attributes>
        </label>
        <label>
          <name>visible_picture_edge</name>
          <color>#9e96c3</color>
          <attributes>
          </attributes>
        </label>
        <label>
          <name>board</name>
          <color>#3d3df5</color>
          <attributes>
          </attributes>
        </label>
      </labels>
      <segments>
        <segment>
          <id>3524</id>
          <start>0</start>
          <stop>0</stop>
          <url>http://cvat.sharetheboard.com/?id=3524</url>
        </segment>
      </segments>
      <owner>
        <username>f_nawrocki</username>
        <email>nawrocki.fil@gmail.com</email>
      </owner>
      <assignee>
        <username>f_nawrocki</username>
        <email>nawrocki.fil@gmail.com</email>
      </assignee>
    </task>
    <dumped>2023-10-23 09:15:42.263382+00:00</dumped>
  <frame_source type="video" path="video/blackboard_047.mp4"><video name="blackboard_047.mp4" frame="600" /></frame_source></meta>
  <image id="0" name="blackboard_047.mp4_frame_600.png" width="1920" height="1080">
    <polygon label="visible_corner" occluded="0" source="manual" points="0.00,19.58;1911.17,27.65;1901.38,955.15;0.58,972.29" z_order="0">
    </polygon>
    <polygon label="content" occluded="0" source="manual" points="49.09,47.24;49.45,21.20;15.85,21.20;21.13,32.24;22.81,45.44" z_order="0">
      <attribute name="Difficult">false</attribute>
    </polygon>
    <polygon label="person" occluded="0" source="manual" points="176.91,1079.88;168.14,1065.94;171.75,1047.37;161.43,1003.51;166.08,961.72;171.24,884.32;176.91,808.47;181.56,671.74;195.49,549.45;218.19,496.82;248.63,468.44;272.89,455.03;336.87,430.78;414.78,390.53;439.03,378.66;466.89,344.61;524.17,295.59;543.77,272.37;560.29,235.74;588.15,200.13;622.72,212.52;643.87,165.56;644.91,147.50;645.42,125.32;670.19,88.17;678.44,52.05;658.84,41.21;627.88,31.41;594.34,26.76;557.71,27.80;568.03,91.26;560.80,112.42;510.75,173.30;443.67,213.03;381.24,254.31;303.33,281.14;232.64,289.40;161.43,280.11;115.51,278.56;85.59,271.85;56.18,207.36;56.69,170.72;77.85,155.24;42.76,112.42;47.40,86.10;21.20,34.20;0.00,0.40;0.00,1079.36" z_order="0">
      <attribute name="hand_only">false</attribute>
    </polygon>
    <points label="visible_corner" occluded="0" source="manual" points="1910.21,29.52;1900.10,952.36" z_order="0">
    </points>
    <points label="invisible_corner" occluded="0" source="manual" points="2.90,970.00;0.40,20.30" z_order="0">
    </points>
    <polyline label="content_white" occluded="0" source="manual" points="1021.80,677.70;1006.40,676.90;976.50,679.10;952.80,681.10;920.60,684.60;892.90,687.60;858.50,689.70;833.30,691.60;810.50,693.70;795.40,695.40;780.10,697.60;756.70,702.00;734.40,705.50;716.60,708.10;707.00,709.20;687.90,709.50;666.30,708.50;644.80,707.60;620.60,706.80;612.00,706.10;605.20,703.10;601.50,678.80;599.10,648.70;596.90,621.80;594.10,602.30;589.10,586.60;587.30,578.60;590.30,573.20;594.10,572.30;609.60,572.20;639.70,573.90;680.80,573.70;707.90,572.50" z_order="0">
    </polyline>
    <polyline label="content_white" occluded="0" source="manual" points="616.21,573.24;615.21,570.24;617.41,567.74;622.41,568.24;627.41,570.34;631.61,573.14;636.71,577.24;639.31,580.24;640.91,583.84;640.61,587.94;638.91,593.44;640.11,595.64;647.11,596.84;656.51,597.04;662.61,594.64;664.71,591.14;663.91,586.64;660.71,582.44;657.41,579.74;654.41,578.74;650.31,578.24;648.71,580.34;649.51,585.14;653.61,590.04;662.71,598.74;679.61,612.94" z_order="0">
    </polyline>
    <polyline label="content_white" occluded="0" source="manual" points="720.41,601.94;701.91,601.74;691.01,600.94;672.81,597.74;651.31,591.94;627.51,584.44;608.61,577.14;589.51,566.54;572.41,551.04;559.91,534.24;553.91,519.94;549.71,505.34" z_order="0">
    </polyline>
    <polyline label="content_white" occluded="0" source="manual" points="518.33,478.81;493.63,477.31;467.23,477.81;422.23,479.71;381.43,480.21;340.93,478.21;320.43,475.71;309.63,470.51;302.03,462.31;307.73,441.01" z_order="0">
    </polyline>
    <polyline label="content_white" occluded="0" source="manual" points="302.90,471.30;274.70,466.80;249.90,466.80" z_order="0">
    </polyline>
    <polyline label="content_white" occluded="0" source="manual" points="273.65,500.56;271.35,492.26;266.35,486.46" z_order="0">
    </polyline>
    <polyline label="content_white" occluded="0" source="manual" points="249.34,506.66;257.34,509.86;267.45,512.06;272.65,517.26;273.15,520.96;268.95,522.96;261.74,523.66;257.74,521.56;260.54,515.66;268.65,509.46;273.95,506.76" z_order="0">
    </polyline>
    <polyline label="content_white" occluded="0" source="manual" points="288.95,528.56;310.65,536.06;323.54,536.66" z_order="0">
    </polyline>
    <polyline label="content_white" occluded="0" source="manual" points="320.45,516.46;328.95,533.06;340.04,543.46;350.34,548.46;360.95,548.26;365.45,542.56;363.65,535.46;355.84,528.16" z_order="0">
    </polyline>
    <polyline label="content_white" occluded="0" source="manual" points="337.65,564.36;335.85,570.66;339.04,578.56" z_order="0">
    </polyline>
    <polyline label="content_white" occluded="0" source="manual" points="355.35,579.96;360.04,599.96" z_order="0">
    </polyline>
    <polyline label="content_white" occluded="0" source="manual" points="379.78,552.78;392.67,556.88;408.37,556.38;415.28,549.98;407.07,541.28;410.37,552.28;417.87,557.58;433.47,561.58;449.97,565.68;465.57,570.28" z_order="0">
    </polyline>
    <polyline label="content_white" occluded="0" source="manual" points="438.47,550.58;451.57,551.28;452.17,560.28;467.97,569.18" z_order="0">
    </polyline>
    <polyline label="content_white" occluded="0" source="manual" points="455.27,564.38;470.87,565.18;477.37,565.28;482.17,564.48;487.87,560.18;489.47,551.88;485.97,531.98;480.87,507.88" z_order="0">
    </polyline>
    <polyline label="content_white" occluded="0" source="manual" points="498.00,502.60;502.20,526.30;504.80,543.50;508.90,572.50;508.40,576.90" z_order="0">
    </polyline>
    <polyline label="content_white" occluded="0" source="manual" points="510.45,476.30;517.65,492.80;523.55,511.20;528.85,532.10;532.85,553.10;536.25,574.60;537.55,591.60;537.45,607.90;534.15,622.40;530.05,629.20;523.95,634.70;515.45,639.10;503.35,642.70;485.45,645.20;464.95,647.10;433.95,648.10;399.65,649.10;361.65,649.80;332.25,650.00;312.85,647.70;293.25,642.30;275.45,633.00;256.65,613.00;242.35,590.00;232.45,562.10;222.65,530.30;214.05,501.60" z_order="0">
    </polyline>
    <polyline label="content_white" occluded="0" source="manual" points="532.62,379.82;476.32,379.82;436.52,380.32" z_order="0">
    </polyline>
    <polyline label="content_white" occluded="0" source="manual" points="417.82,390.72;416.52,401.92;409.52,425.92;404.92,439.52;403.12,451.72;405.62,456.82;416.12,455.32;430.52,451.82;437.02,451.62;441.62,454.22;437.82,457.42;433.12,458.32;427.72,457.02;426.92,451.52;429.22,447.22;434.62,445.12;441.42,447.82;449.02,452.42;456.82,456.42;462.12,452.02;467.12,442.52;469.62,427.82;475.42,397.42;467.52,426.72;464.22,441.52;465.32,450.42;472.92,456.62;483.52,459.22;497.12,459.82;507.42,459.62;516.32,458.62;519.72,455.92;519.62,450.12;514.52,447.12;505.82,445.02;496.82,442.72;490.22,440.12;487.62,436.42;491.02,430.92;498.92,424.52;508.12,418.92;516.42,414.42;524.22,410.72" z_order="0">
    </polyline>
    <polyline label="content_white" occluded="0" source="manual" points="379.74,425.92;382.03,429.82;381.64,434.72" z_order="0">
    </polyline>
    <polyline label="content_white" occluded="0" source="manual" points="387.44,437.42;393.94,445.82;393.64,451.82;388.24,455.92;378.84,458.22;365.14,457.52;354.53,456.22;343.03,452.72;334.34,447.42;328.34,435.82" z_order="0">
    </polyline>
    <polyline label="content_white" occluded="0" source="manual" points="362.14,436.62;354.84,428.62" z_order="0">
    </polyline>
    <polyline label="content_white" occluded="0" source="manual" points="379.40,407.82;387.17,412.57" z_order="0">
    </polyline>
    <polyline label="content_white" occluded="0" source="manual" points="451.72,602.63;451.00,579.59" z_order="0">
    </polyline>
    <polyline label="content_white" occluded="0" source="manual" points="576.78,244.46;593.58,231.66;607.98,221.96;611.48,215.96;613.98,210.36" z_order="0">
    </polyline>
    <polyline label="content_white" occluded="0" source="manual" points="590.98,206.86;594.88,213.46" z_order="0">
    </polyline>
    <polyline label="content_white" occluded="0" source="manual" points="679.11,425.68;700.51,431.78;724.31,437.68" z_order="0">
    </polyline>
    <polyline label="content_white" occluded="0" source="manual" points="723.51,351.22;717.21,357.82;712.91,364.62;714.41,370.22;717.81,372.72;723.31,373.62;728.31,371.52;731.61,367.22;731.01,361.12;728.41,354.72;724.31,346.92;725.31,343.52;731.61,339.22;736.11,337.92;738.91,339.02;738.61,342.02;734.91,344.62;730.51,347.12;730.01,350.52;735.11,353.52;741.81,356.82;747.31,358.32;752.61,357.72;758.21,354.62;765.61,346.82;770.31,336.82;771.41,324.92;771.61,309.82;772.01,295.62" z_order="0">
    </polyline>
    <polyline label="content_white" occluded="0" source="manual" points="789.11,285.62;793.61,305.32" z_order="0">
    </polyline>
    <polyline label="content_white" occluded="0" source="manual" points="605.47,475.79;618.27,479.09;630.87,480.79;638.37,482.19;644.07,484.59;645.67,487.49;640.97,490.49;628.67,493.89;617.67,495.79;611.67,494.99;611.87,491.39;617.17,485.99;626.07,478.39;627.87,473.69" z_order="0">
    </polyline>
    <polyline label="content_white" occluded="0" source="manual" points="662.87,480.99;670.97,489.69;676.07,501.99;676.47,512.29;674.57,520.39;669.57,527.99;661.77,534.19;651.57,540.09;640.37,544.79;622.47,550.49" z_order="0">
    </polyline>
    <polyline label="content_white" occluded="0" source="manual" points="696.77,534.49;696.87,540.09;700.27,546.59" z_order="0">
    </polyline>
    <polyline label="content_white" occluded="0" source="manual" points="718.80,507.30;700.90,503.50;684.20,498.70;674.40,495.10" z_order="0">
    </polyline>
    <polyline label="content_white" occluded="0" source="manual" points="624.68,618.28;638.18,623.38;646.18,628.58;638.08,631.88;627.48,633.78;630.18,627.88;632.98,623.28" z_order="0">
    </polyline>
    <polyline label="content_white" occluded="0" source="manual" points="642.38,609.38;645.78,615.18;645.68,621.28" z_order="0">
    </polyline>
    <polyline label="content_white" occluded="0" source="manual" points="660.88,624.48;669.08,633.58;672.68,642.98;672.18,650.58;667.98,657.18;660.88,663.08;650.38,667.48;641.38,669.98;633.08,672.08;623.98,673.08" z_order="0">
    </polyline>
    <polyline label="content_white" occluded="0" source="manual" points="672.18,632.88;680.78,644.38;693.28,649.38;708.18,651.48;719.88,652.48;723.68,648.68;719.38,642.08;709.18,629.58;723.48,643.08;733.98,646.18" z_order="0">
    </polyline>
    <polyline label="content_white" occluded="0" source="manual" points="727.01,672.90;728.71,676.70;725.21,680.00" z_order="0">
    </polyline>
    <polyline label="content_white" occluded="0" source="manual" points="689.71,671.10;692.81,678.40" z_order="0">
    </polyline>
    <polyline label="content_white" occluded="0" source="manual" points="681.71,662.20;680.91,672.00" z_order="0">
    </polyline>
    <polyline label="content_white" occluded="0" source="manual" points="785.00,694.70;788.50,669.40;791.30,647.10;793.70,625.80;794.90,614.80" z_order="0">
    </polyline>
    <polyline label="content_white" occluded="0" source="manual" points="819.27,628.00;819.67,642.00;825.77,647.00;837.47,649.30;851.57,649.10;862.87,647.20;872.67,644.20;878.87,640.20;884.37,633.80;885.07,624.90;881.37,620.20;876.97,617.60;869.27,617.10;865.77,620.00;867.07,623.70;873.77,630.10;883.77,637.50" z_order="0">
    </polyline>
    <polyline label="content_white" occluded="0" source="manual" points="864.20,602.04;867.90,609.34" z_order="0">
    </polyline>
    <polyline label="content_white" occluded="0" source="manual" points="881.30,603.94;885.60,615.24" z_order="0">
    </polyline>
    <polyline label="content_white" occluded="0" source="manual" points="904.40,622.54;913.50,630.84;915.90,635.64;913.60,640.34;908.00,642.14;899.90,640.94" z_order="0">
    </polyline>
    <polyline label="content_white" occluded="0" source="manual" points="932.40,588.64;934.40,606.34;935.10,617.34;935.30,626.14;934.10,631.74;932.10,638.24;934.70,643.14;944.70,645.64;954.50,645.84;967.70,645.34;969.70,642.14;964.20,626.84;970.30,640.94;980.40,645.54;991.10,649.44;1000.60,650.54;1006.90,650.34;1011.20,647.64;1013.40,642.94;1012.60,637.74;1009.70,634.24;1004.20,632.94;999.30,633.14;995.30,637.44;998.50,640.44;1004.60,642.64;1010.60,644.54;1016.90,646.84;1019.80,646.04;1018.70,642.34" z_order="0">
    </polyline>
    <polyline label="content_white" occluded="0" source="manual" points="1006.80,625.84;1010.20,619.94;1010.60,613.94" z_order="0">
    </polyline>
    <polyline label="content_white" occluded="0" source="manual" points="954.50,606.84;951.80,614.44" z_order="0">
    </polyline>
    <polyline label="content_white" occluded="0" source="manual" points="884.50,594.64;873.30,586.24;865.50,580.14;865.50,575.94;869.50,573.24;873.80,574.04;876.90,575.44;875.40,578.54;870.10,581.74;857.50,587.04;854.10,589.84" z_order="0">
    </polyline>
    <polyline label="content_white" occluded="0" source="manual" points="847.60,597.24;863.60,597.14;874.60,594.44;886.10,589.54;895.20,583.84;900.60,579.04;903.00,573.04;903.10,566.54;900.20,558.44;894.90,551.54;881.50,540.74" z_order="0">
    </polyline>
    <polyline label="content_white" occluded="0" source="manual" points="867.90,557.34;884.00,558.44;916.90,563.34;951.60,566.14;977.20,568.24;997.60,569.44;1013.70,568.04;1024.10,569.14;1027.40,571.44;1027.10,576.94;1027.30,585.94" z_order="0">
    </polyline>
    <polyline label="content_white" occluded="0" source="manual" points="898.11,578.30;898.58,571.34;895.22,566.18;890.66,562.58;880.82,556.82;875.42,554.42;871.70,553.58" z_order="0">
    </polyline>
    <polyline label="content_white" occluded="0" source="manual" points="884.05,514.46;901.25,522.96;915.05,526.86;928.55,528.26;942.45,528.26;954.75,527.16;965.55,524.76;973.95,521.46;982.95,515.76" z_order="0">
    </polyline>
    <polyline label="content_white" occluded="0" source="manual" points="955.05,495.96;956.05,508.86" z_order="0">
    </polyline>
    <polyline label="content_white" occluded="0" source="manual" points="928.25,493.16;931.75,503.36" z_order="0">
    </polyline>
    <polyline label="content_white" occluded="0" source="manual" points="1030.57,530.59;1053.07,529.79;1050.97,526.39;1041.18,520.39;1044.57,519.09;1050.68,519.99" z_order="0">
    </polyline>
    <polyline label="content_white" occluded="0" source="manual" points="1055.12,582.06;1029.92,581.92;1007.45,582.06;978.65,583.21;949.13,584.94;916.01,586.24;891.68,588.25;868.35,590.99;852.65,592.43" z_order="0">
    </polyline>
    <polyline label="content_white" occluded="0" source="manual" points="1035.95,640.95;1034.95,620.25;1033.65,606.25;1031.05,596.05;1024.05,580.05" z_order="0">
    </polyline>
    <polyline label="content_white" occluded="0" source="manual" points="1053.90,520.50;1069.20,524.50;1067.70,528.10;1057.00,529.30;1069.70,537.60" z_order="0">
    </polyline>
  </image>
</annotations>